{
  "generated_at": "2026-05-03T06:20:32.869635+00:00",
  "semesters": [
    {
      "name": "Spring 2026",
      "enrolment_start": "2026-04-01",
      "enrolment_last": "2026-04-24",
      "final_exam_start": "2026-07-06",
      "peak_start": "2026-03-18",
      "peak_end": "2026-04-24"
    },
    {
      "name": "Summer 2026",
      "enrolment_start": "2026-06-15",
      "enrolment_last": "2026-07-23",
      "final_exam_start": "2026-08-17",
      "peak_start": "2026-07-06",
      "peak_end": "2026-07-23"
    },
    {
      "name": "Autumn 2026",
      "enrolment_start": "2026-08-19",
      "enrolment_last": "2026-10-02",
      "final_exam_start": "2026-12-07",
      "peak_start": "2026-08-17",
      "peak_end": "2026-10-02"
    }
  ]
}